MANIFEST.in
setup.cfg
setup.py
MirskUtils.egg-info/PKG-INFO
MirskUtils.egg-info/SOURCES.txt
MirskUtils.egg-info/dependency_links.txt
MirskUtils.egg-info/requires.txt
MirskUtils.egg-info/top_level.txt
mirskutils/__init__.py
mirskutils/_version.py
mirskutils/backends.py
mirskutils/decorators.py
mirskutils/fields.py
mirskutils/forms.py
mirskutils/middleware.py
mirskutils/models.py
mirskutils/nosql.py
mirskutils/sekizai.py
mirskutils/shortcuts.py
mirskutils/template.py
mirskutils/views.py
mirskutils/widgets.py
mirskutils.egg-info/SOURCES.txt
mirskutils/api/__init__.py
mirskutils/api/authentication.py
mirskutils/api/fields.py
mirskutils/api/resources.py
mirskutils/api/serializers.py
mirskutils/conf/app_template/__init__.py
mirskutils/conf/app_template/admin.py
mirskutils/conf/app_template/forms.py
mirskutils/conf/app_template/models.py
mirskutils/conf/app_template/resources.py
mirskutils/conf/app_template/tests.py
mirskutils/conf/app_template/urls.py
mirskutils/conf/app_template/views.py
mirskutils/conf/app_template/management/__init__.py
mirskutils/conf/app_template/management/commands/__init__.py
mirskutils/conf/app_template/management/commands/example.py
mirskutils/conf/app_template/static/app_name/app_name.css
mirskutils/conf/app_template/static/app_name/app_name.js
mirskutils/conf/app_template/templates/app_name/app_name.html
mirskutils/conf/project_template/.gitignore
mirskutils/conf/project_template/README.md
mirskutils/conf/project_template/manage.py
mirskutils/conf/project_template/wsgi.py
mirskutils/conf/project_template/conf/apache-site.cfg
mirskutils/conf/project_template/conf/gitignore
mirskutils/conf/project_template/conf/requirements.txt
mirskutils/conf/project_template/conf/sample.local_settings.py
mirskutils/conf/project_template/conf/uwsgi.sample.ini
mirskutils/conf/project_template/conf/uwsgi.sample.xml
mirskutils/conf/project_template/docs/Makefile
mirskutils/conf/project_template/docs/source/conf.py
mirskutils/conf/project_template/docs/source/index.rst
mirskutils/conf/project_template/docs/source/_static/darkstrap.css
mirskutils/conf/project_template/docs/source/_static/project_template-docs.css
