Metadata-Version: 1.0
Name: mirskutils
Version: 0.2.0
Summary: Mirsky Utility Functions
Home-page: http://mirskytech.github.io/mirskutils/
Author: Andrew
Author-email: andrew@mirsky.net
License: UNKNOWN
Platform: UNKNOWN
